otaro/__init__.py
otaro/parsing.py
otaro/providers.py
otaro/rule_utils.py
otaro/rules.py
otaro/task.py
otaro/task_utils.py
otaro/types.py
otaro/api/__init__.py
otaro/api/server.py
otaro/prompts/__init__.py
otaro/prompts/system_prompt.py
otaro/prompts/user_prompt.py
otaro-0.0.12.dist-info/METADATA
otaro-0.0.12.dist-info/WHEEL
otaro-0.0.12.dist-info/entry_points.txt
otaro-0.0.12.dist-info/RECORD
